<?xml version="1.0" encoding="utf-8"?>
<deployment>
  <id>b80fa34c-c7e3-4f78-b324-77e29c471f70</id>
  <author>N/A</author>
  <deployer>Push-Deployer</deployer>
  <authorEmail>N/A</authorEmail>
  <message>Created via a push deployment</message>
  <progress></progress>
  <status>Success</status>
  <statusText></statusText>
  <lastSuccessEndTime>2025-12-04T16:45:12.4852532Z</lastSuccessEndTime>
  <receivedTime>2025-12-04T16:39:32.4967212Z</receivedTime>
  <startTime>2025-12-04T16:39:33.8998037Z</startTime>
  <endTime>2025-12-04T16:45:12.4852532Z</endTime>
  <complete>True</complete>
  <is_temp>False</is_temp>
  <is_readonly>True</is_readonly>
  <buildSummary />
</deployment>